soup2dict/__init__.py
soup2dict-2.0.0.dist-info/LICENSE
soup2dict-2.0.0.dist-info/WHEEL
soup2dict-2.0.0.dist-info/METADATA
soup2dict-2.0.0.dist-info/RECORD
